isitinstalled/__init__.py
isitinstalled/checker.py
isitinstalled/cli.py
isitinstalled-0.1.dist-info/METADATA
isitinstalled-0.1.dist-info/WHEEL
isitinstalled-0.1.dist-info/entry_points.txt
isitinstalled-0.1.dist-info/top_level.txt
isitinstalled-0.1.dist-info/RECORD
