Metadata-Version: 2.4
Name: isitinstalled
Version: 0.1
Requires-Dist: typer
Requires-Dist: rich
Dynamic: requires-dist
